[
  {
    "title": "Walking up stairs",
    "description": "Travel can be a real work out. We have some tips on how to burn those calories fast.",
    "readTime": 1,
    "imageUrl": "./images/1.jpg"
  },
  {
    "title": "Forms on Tablets a comprehensive guide",
    "description": "When is a Name not just a Name? When it's in need of validatation!'",
    "readTime": 2,
    "imageUrl": "./images/2.jpg"
  },
  {
    "title": "10 App colour pallettes that will get you out of bed in the morning",
    "description": "These hues have been curated by our experts to say 'Hey you! Wake up!'",
    "readTime": 3,
    "imageUrl": "./images/3.jpg"
  },
  {
    "title": "2H Media",
    "description": "H will indicate how hard the lead of a pencil is. To make this clear, look at the range mentioned above. Travelling upwards from H to 2H will mean a harder graphite core. As 2H will be harder than an H, a 6H is really, really hard but will produce lighter and thinner lines than the rest.",
    "readTime": 12,
    "imageUrl": "./images/4.jpg"
  },
  {
    "title": "Title1",
    "description": "Description1",
    "readTime": 1,
    "imageUrl": "./images/5.jpg"
  },
  {
    "title": "Title2",
    "description": "Description2",
    "readTime": 2,
    "imageUrl": "./images/6.jpg"
  },
  {
    "title": "Title1",
    "description": "Description7",
    "readTime": 1,
    "imageUrl": "./images/7.jpg"
  },
  {
    "title": "Title2",
    "description": "Description8",
    "readTime": 2,
    "imageUrl": "./images/8.jpg"
  },
  {
    "title": "Title1",
    "description": "Description9",
    "readTime": 1,
    "imageUrl": "./images/9.jpg"
  },
  {
    "title": "Title2",
    "description": "Description10",
    "readTime": 2,
    "imageUrl": "./images/10.jpg"
  },
  {
    "title": "Title1",
    "description": "Description11",
    "readTime": 1,
    "imageUrl": "./images/11.jpg"
  },
  {
    "title": "Title2",
    "description": "Description12",
    "readTime": 2,
    "imageUrl": "./images/12.jpg"
  },
  {
    "title": "Title1",
    "description": "Description13",
    "readTime": 1,
    "imageUrl": "./images/13.jpg"
  },
  {
    "title": "Title2",
    "description": "Description2",
    "readTime": 2,
    "imageUrl": "./images/14.jpg"
  },
  {
    "title": "Title1",
    "description": "Description15",
    "readTime": 1,
    "imageUrl": "./images/15.jpg"
  },
  {
    "title": "Title2",
    "description": "Description16",
    "readTime": 2,
    "imageUrl": "./images/16.jpg"
  },
  {
    "title": "Title1",
    "description": "Description17",
    "readTime": 1,
    "imageUrl": "./images/17.jpg"
  },
  {
    "title": "Title2",
    "description": "Description18",
    "readTime": 2,
    "imageUrl": "./images/18.jpg"
  },
  {
    "title": "Title1",
    "description": "Description19",
    "readTime": 1,
    "imageUrl": "./images/19.jpg"
  },
  {
    "title": "Title2",
    "description": "Description20",
    "readTime": 2,
    "imageUrl": "./images/20.jpg"
  },
  {
    "title": "Title1",
    "description": "Description21",
    "readTime": 1,
    "imageUrl": "./images/21.jpg"
  },
  {
    "title": "Title1",
    "description": "Description22",
    "readTime": 1,
    "imageUrl": "./images/22.jpg"
  },
  {
    "title": "Title2",
    "description": "Description23",
    "readTime": 2,
    "imageUrl": "./images/23.jpg"
  },
  {
    "title": "Title1",
    "description": "Description24",
    "readTime": 1,
    "imageUrl": "./images/24.jpg"
  }
]